{
  "id": 12319,
  "name": "Crier hat",
  "resizeX": 128,
  "resizeY": 128,
  "resizeZ": 128,
  "xan2d": 184,
  "yan2d": 225,
  "zan2d": 0,
  "cost": 5000,
  "isTradeable": true,
  "stackable": 0,
  "inventoryModel": 28737,
  "members": true,
  "zoom2d": 779,
  "xOffset2d": 0,
  "yOffset2d": 0,
  "ambient": 0,
  "contrast": 0,
  "options": [
    null,
    null,
    "Take",
    null,
    null
  ],
  "interfaceOptions": [
    null,
    "Wear",
    null,
    null,
    "Drop"
  ],
  "maleModel0": 27149,
  "maleModel1": -1,
  "maleModel2": -1,
  "maleOffset": 0,
  "maleHeadModel": 28764,
  "maleHeadModel2": -1,
  "femaleModel0": 27149,
  "femaleModel1": -1,
  "femaleModel2": -1,
  "femaleOffset": 0,
  "femaleHeadModel": 28797,
  "femaleHeadModel2": -1,
  "notedID": 12320,
  "notedTemplate": -1,
  "team": 0,
  "shiftClickDropIndex": -2,
  "placeholderId": 15900,
  "placeholderTemplateId": -1
}