{
  "id": 13641,
  "name": "Farmer\u0027s boro trousers",
  "resizeX": 128,
  "resizeY": 128,
  "resizeZ": 128,
  "xan2d": 1508,
  "yan2d": 741,
  "zan2d": 1091,
  "cost": 50,
  "isTradeable": false,
  "stackable": 0,
  "inventoryModel": 31040,
  "members": true,
  "zoom2d": 1916,
  "xOffset2d": 0,
  "yOffset2d": -3,
  "ambient": 0,
  "contrast": 0,
  "options": [
    null,
    null,
    "Take",
    null,
    null
  ],
  "interfaceOptions": [
    null,
    "Wear",
    null,
    null,
    "Drop"
  ],
  "maleModel0": -1,
  "maleModel1": -1,
  "maleModel2": -1,
  "maleOffset": 0,
  "maleHeadModel": -1,
  "maleHeadModel2": -1,
  "femaleModel0": 31031,
  "femaleModel1": -1,
  "femaleModel2": -1,
  "femaleOffset": 0,
  "femaleHeadModel": -1,
  "femaleHeadModel2": -1,
  "notedID": -1,
  "notedTemplate": -1,
  "team": 0,
  "shiftClickDropIndex": -2,
  "placeholderId": 18471,
  "placeholderTemplateId": -1
}