{
  "id": 6317,
  "name": "Red topaz machete",
  "resizeX": 128,
  "resizeY": 128,
  "resizeZ": 128,
  "xan2d": 200,
  "yan2d": 88,
  "zan2d": 0,
  "cost": 2000,
  "isTradeable": true,
  "stackable": 0,
  "inventoryModel": 2841,
  "members": true,
  "colorFind": [
    90,
    70
  ],
  "colorReplace": [
    -4160,
    49
  ],
  "zoom2d": 770,
  "xOffset2d": -2,
  "yOffset2d": -12,
  "ambient": 0,
  "contrast": 0,
  "options": [
    null,
    null,
    "Take",
    null,
    null
  ],
  "interfaceOptions": [
    null,
    "Wield",
    null,
    null,
    "Drop"
  ],
  "maleModel0": 566,
  "maleModel1": -1,
  "maleModel2": -1,
  "maleOffset": 0,
  "maleHeadModel": -1,
  "maleHeadModel2": -1,
  "femaleModel0": 566,
  "femaleModel1": -1,
  "femaleModel2": -1,
  "femaleOffset": 6,
  "femaleHeadModel": -1,
  "femaleHeadModel2": -1,
  "notedID": 6318,
  "notedTemplate": -1,
  "team": 0,
  "shiftClickDropIndex": -2,
  "placeholderId": 18723,
  "placeholderTemplateId": -1
}